PySimulationEngine/Agent.py
PySimulationEngine/Display.py
PySimulationEngine/LayoutWidget.py
PySimulationEngine/MainWindow.py
PySimulationEngine/Simulation.py
PySimulationEngine/StartPauseButton.py
PySimulationEngine/Statistic.py
PySimulationEngine/WorldView.py
PySimulationEngine/WorldViewUpdater.py
PySimulationEngine/__init__.py
PySimulationEngine-0.1.3.dist-info/LICENSE
PySimulationEngine-0.1.3.dist-info/METADATA
PySimulationEngine-0.1.3.dist-info/WHEEL
PySimulationEngine-0.1.3.dist-info/top_level.txt
PySimulationEngine-0.1.3.dist-info/RECORD
