Metadata-Version: 2.1
Name: PySimulationEngine
Version: 0.1.3
Summary: Python Library to run a simulation with user objects and AIs and display it all through a simple GUI.
Author: Cristos Criniti
License: MIT
License-File: LICENSE
Requires-Dist: pyqt5 (==5.15.7)
